MANIFEST.in
RELEASE-VERSION
pavement.py
paver-minilib.zip
setup.py
version.py
arduino_servo/__init__.py
arduino_servo.egg-info/PKG-INFO
arduino_servo.egg-info/SOURCES.txt
arduino_servo.egg-info/dependency_links.txt
arduino_servo.egg-info/top_level.txt
arduino_servo/Arduino/Servo/Servo.cpp
arduino_servo/Arduino/Servo/Servo.h
arduino_servo/Arduino/Servo/Servo.o
arduino_servo/Arduino/Servo/keywords.txt
arduino_servo/Arduino/Servo/examples/Knob/Knob.ino
arduino_servo/Arduino/Servo/examples/Sweep/Sweep.ino
arduino_servo/lib/C-Array-Defs.tar.gz