Metadata-Version: 1.0
Name: arduino-servo
Version: 0.1
Summary: Simple C classes for arrays of standard numeric types.
Home-page: https://github.com/wheeler-microfluidics/arduino-servo
Author: Christian Fobel
Author-email: christian@fobel.net
License: GPL
Keywords: c++ array simple
Platform: UNKNOWN
